<settings xmlns="http://maven.apache.org/SETTINGS/1.0.0"
          xmlns:xsi="http://www.w3.org/2001/XMLSchema-instance"
          xsi:schemaLocation="http://maven.apache.org/SETTINGS/1.0.0
                              https://maven.apache.org/xsd/settings-1.0.0.xsd">

    <mirrors>
        <mirror>
            <id>central</id>
            <mirrorOf>central</mirrorOf>
            <url>https://repo.maven.apache.org/maven2</url>
        </mirror>
    </mirrors>

    <profiles>
        <profile>
            <id>profile1</id>
            <activation>
                <activeByDefault>true</activeByDefault>
            </activation>
            <properties>
                <property-name>property-value</property-name>
            </properties>
            <repositories>
                <repository>
                    <id>central</id>
                    <url>https://repo.maven.apache.org/maven2</url>
                    <releases>
                        <enabled>true</enabled>
                    </releases>
                    <snapshots>
                        <enabled>true</enabled>
                    </snapshots>
                </repository>
            </repositories>
            <pluginRepositories>
                <pluginRepository>
                    <id>central</id>
                    <url>https://repo.maven.apache.org/maven2</url>
                    <releases>
                        <enabled>true</enabled>
                    </releases>
                    <snapshots>
                        <enabled>true</enabled>
                    </snapshots>
                </pluginRepository>
            </pluginRepositories>
        </profile>
    </profiles>

    <activeProfiles>
        <activeProfile>profile1</activeProfile>
    </activeProfiles>
</settings>
